[{"title":"$J$-Stability in non-archimedean dynamics","state":"arXiv","links":{"arXiv":",https://arxiv.org/abs/2102.05841","journal":""},"authors":["Robert L. Benedetto","Junghun Lee"],"journal":{"year":"2021","publisher":"","pages":"","number":"","name":"arXiv:2102.05841 [math.DS]"}},{"title":"THE VALUES OF THE RIEMANN ZETA-FUNCTION ON DISCRETE SETS","state":"arXiv","authors":["Junghun Lee","A. Sourmelidis","J. Steuding","A. Suriajaya"],"links":{"journal":"https://projecteuclid.org/euclid.aspm/1590597092","arXiv":"https://arxiv.org/abs/1710.11367"},"journal":{"publisher":"Mathematical Society of Japan","year":"2020","name":"Adv. Stud. Pure Math.","number":"84","pages":"315-334"}},{"state":"published","authors":["Junghun Lee"],"title":"$J$-stability of expanding maps in non-Archimedean dynamics","links":{"arXiv":"","journal":"https://www.cambridge.org/core/journals/ergodic-theory-and-dynamical-systems/article/abs/j-stability-of-expanding-maps-in-nonarchimedean-dynamics/6ED1A3C12C31389C11CCDD305052BD2D"},"journal":{"name":"Ergo. Th. & Dynam. Sys.","number":"39","year":"2019","pages":"1002-1019","publisher":"Cambridge University Press"}},{"links":{"journal":"https://www.sciencedirect.com/science/article/pii/S0022247X16303882","arXiv":"https://arxiv.org/abs/1512.04169"},"journal":{"publisher":"Elsevier","year":"2017","number":"445","name":"J. Math. Anal. Appl.","pages":"125-138"},"state":"published","authors":["Junghun Lee","A. Suriajaya"],"title":"An ergodic value distribution of certain meromorphic functions"},{"state":"published","authors":["Junghun Lee","T. Onozuka","A. Suriajaya"],"title":"Some probabilistic value distributions of the Riemann Zeta function and its derivatives","links":{"arXiv":"","journal":"https://projecteuclid.org/euclid.pja/1469104540"},"journal":{"pages":"82-83","publisher":"The Japan Academy","year":"2016","name":"Proc. Japan Acad. Ser. A Math. Sci.","number":"92 no.7"}},{"authors":["Junghun Lee"],"links":{"journal":"https://projecteuclid.org/euclid.pja/1459516320","arXiv":""},"title":"An alternative proof of the non-Archimedean Montel theorem for rational dynamics","state":"published","journal":{"name":"Proc. Japan Acad. Ser. A Math. Sci.","pages":"56-58","number":"92 no.4","publisher":"The Japan Academy","year":"2016"}},{"title":"An alternative proof of the non-Archimedean Montel theorem for polynomial dynamics, Advances in Non-Archimedean Analysis","journal":{"publisher":"American Mathematical Society","name":"Contemp. Math.","number":"665","year":"2016","pages":"133-137"},"authors":["Junghun Lee"],"state":"published","links":{"arXiv":"https://arxiv.org/pdf/1505.05611.pdf","journal":"https://www.ams.org/books/conm/665/"}},{"links":{"journal":"","arXiv":"https://arxiv.org/abs/1505.04249"},"journal":{"number":"","name":"ArXiv:1505.04249 [math.DS]","year":"2015","publisher":"","pages":""},"title":"The Artin-Mazur zeta functions of certain non-Archimedean dynamical systems","authors":["Junghun Lee"],"state":"arXiv"}]